[
  {
    "season": 2017,
    "seasonType": "regular",
    "week": 7,
    "polls": [
      {
        "poll": "AP Top 25",
        "ranks": [
          {
            "rank": 1,
            "school": "Alabama",
            "conference": "SEC",
            "firstPlaceVotes": 43,
            "points": 1507
          },
          {
            "rank": 2,
            "school": "Clemson",
            "conference": "ACC",
            "firstPlaceVotes": 18,
            "points": 1481
          },
          {
            "rank": 3,
            "school": "Penn State",
            "conference": "Big Ten",
            "firstPlaceVotes": 0,
            "points": 1370
          },
          {
            "rank": 4,
            "school": "Georgia",
            "conference": "SEC",
            "firstPlaceVotes": 0,
            "points": 1327
          },
          {
            "rank": 5,
            "school": "Washington",
            "conference": "Pac-12",
            "firstPlaceVotes": 0,
            "points": 1284
          },
          {
            "rank": 6,
            "school": "TCU",
            "conference": "Big 12",
            "firstPlaceVotes": 0,
            "points": 1192
          },
          {
            "rank": 7,
            "school": "Wisconsin",
            "conference": "Big Ten",
            "firstPlaceVotes": 0,
            "points": 1127
          },
          {
            "rank": 8,
            "school": "Washington State",
            "conference": "Pac-12",
            "firstPlaceVotes": 0,
            "points": 1094
          },
          {
            "rank": 9,
            "school": "Ohio State",
            "conference": "Big Ten",
            "firstPlaceVotes": 0,
            "points": 1051
          },
          {
            "rank": 10,
            "school": "Auburn",
            "conference": "SEC",
            "firstPlaceVotes": 0,
            "points": 914
          },
          {
            "rank": 11,
            "school": "Miami",
            "conference": "ACC",
            "firstPlaceVotes": 0,
            "points": 908
          },
          {
            "rank": 12,
            "school": "Oklahoma",
            "conference": "Big 12",
            "firstPlaceVotes": 0,
            "points": 851
          },
          {
            "rank": 13,
            "school": "USC",
            "conference": "Pac-12",
            "firstPlaceVotes": 0,
            "points": 795
          },
          {
            "rank": 14,
            "school": "Oklahoma State",
            "conference": "Big 12",
            "firstPlaceVotes": 0,
            "points": 712
          },
          {
            "rank": 15,
            "school": "Virginia Tech",
            "conference": "ACC",
            "firstPlaceVotes": 0,
            "points": 617
          },
          {
            "rank": 16,
            "school": "Notre Dame",
            "conference": "FBS Independents",
            "firstPlaceVotes": 0,
            "points": 583
          },
          {
            "rank": 17,
            "school": "Michigan",
            "conference": "Big Ten",
            "firstPlaceVotes": 0,
            "points": 524
          },
          {
            "rank": 18,
            "school": "South Florida",
            "conference": "American Athletic",
            "firstPlaceVotes": 0,
            "points": 482
          },
          {
            "rank": 19,
            "school": "San Diego State",
            "conference": "Mountain West",
            "firstPlaceVotes": 0,
            "points": 465
          },
          {
            "rank": 20,
            "school": "NC State",
            "conference": "ACC",
            "firstPlaceVotes": 0,
            "points": 421
          },
          {
            "rank": 21,
            "school": "Michigan State",
            "conference": "Big Ten",
            "firstPlaceVotes": 0,
            "points": 416
          },
          {
            "rank": 22,
            "school": "UCF",
            "conference": "American Athletic",
            "firstPlaceVotes": 0,
            "points": 274
          },
          {
            "rank": 23,
            "school": "Stanford",
            "conference": "Pac-12",
            "firstPlaceVotes": 0,
            "points": 109
          },
          {
            "rank": 24,
            "school": "Texas Tech",
            "conference": "Big 12",
            "firstPlaceVotes": 0,
            "points": 105
          },
          {
            "rank": 25,
            "school": "Navy",
            "conference": "American Athletic",
            "firstPlaceVotes": 0,
            "points": 74
          }
        ]
      },
      {
        "poll": "Coaches Poll",
        "ranks": [
          {
            "rank": 1,
            "school": "Alabama",
            "conference": "SEC",
            "firstPlaceVotes": 57,
            "points": 1617
          },
          {
            "rank": 2,
            "school": "Clemson",
            "conference": "ACC",
            "firstPlaceVotes": 8,
            "points": 1568
          },
          {
            "rank": 3,
            "school": "Penn State",
            "conference": "Big Ten",
            "firstPlaceVotes": 0,
            "points": 1454
          },
          {
            "rank": 4,
            "school": "Washington",
            "conference": "Pac-12",
            "firstPlaceVotes": 0,
            "points": 1404
          },
          {
            "rank": 5,
            "school": "Georgia",
            "conference": "SEC",
            "firstPlaceVotes": 0,
            "points": 1380
          },
          {
            "rank": 6,
            "school": "Wisconsin",
            "conference": "Big Ten",
            "firstPlaceVotes": 0,
            "points": 1243
          },
          {
            "rank": 7,
            "school": "TCU",
            "conference": "Big 12",
            "firstPlaceVotes": 0,
            "points": 1229
          },
          {
            "rank": 8,
            "school": "Ohio State",
            "conference": "Big Ten",
            "firstPlaceVotes": 0,
            "points": 1146
          },
          {
            "rank": 9,
            "school": "Washington State",
            "conference": "Pac-12",
            "firstPlaceVotes": 0,
            "points": 1117
          },
          {
            "rank": 10,
            "school": "Miami",
            "conference": "ACC",
            "firstPlaceVotes": 0,
            "points": 1003
          },
          {
            "rank": 11,
            "school": "Auburn",
            "conference": "SEC",
            "firstPlaceVotes": 0,
            "points": 941
          },
          {
            "rank": 12,
            "school": "Oklahoma",
            "conference": "Big 12",
            "firstPlaceVotes": 0,
            "points": 919
          },
          {
            "rank": 13,
            "school": "USC",
            "conference": "Pac-12",
            "firstPlaceVotes": 0,
            "points": 818
          },
          {
            "rank": 14,
            "school": "Oklahoma State",
            "conference": "Big 12",
            "firstPlaceVotes": 0,
            "points": 788
          },
          {
            "rank": 15,
            "school": "South Florida",
            "conference": "American Athletic",
            "firstPlaceVotes": 0,
            "points": 622
          },
          {
            "rank": 16,
            "school": "Michigan",
            "conference": "Big Ten",
            "firstPlaceVotes": 0,
            "points": 612
          },
          {
            "rank": 17,
            "school": "Virginia Tech",
            "conference": "ACC",
            "firstPlaceVotes": 0,
            "points": 599
          },
          {
            "rank": 18,
            "school": "San Diego State",
            "conference": "Mountain West",
            "firstPlaceVotes": 0,
            "points": 516
          },
          {
            "rank": 19,
            "school": "Notre Dame",
            "conference": "FBS Independents",
            "firstPlaceVotes": 0,
            "points": 498
          },
          {
            "rank": 20,
            "school": "NC State",
            "conference": "ACC",
            "firstPlaceVotes": 0,
            "points": 455
          },
          {
            "rank": 21,
            "school": "UCF",
            "conference": "American Athletic",
            "firstPlaceVotes": 0,
            "points": 273
          },
          {
            "rank": 22,
            "school": "Michigan State",
            "conference": "Big Ten",
            "firstPlaceVotes": 0,
            "points": 261
          },
          {
            "rank": 23,
            "school": "Utah",
            "conference": "Pac-12",
            "firstPlaceVotes": 0,
            "points": 122
          },
          {
            "rank": 24,
            "school": "Navy",
            "conference": "American Athletic",
            "firstPlaceVotes": 0,
            "points": 110
          },
          {
            "rank": 25,
            "school": "Stanford",
            "conference": "Pac-12",
            "firstPlaceVotes": 0,
            "points": 107
          }
        ]
      },
      {
        "poll": "FCS Coaches Poll",
        "ranks": [
          {
            "rank": 1,
            "school": "James Madison",
            "conference": "CAA",
            "firstPlaceVotes": 25,
            "points": 649
          },
          {
            "rank": 2,
            "school": "North Dakota State",
            "conference": "MVFC",
            "firstPlaceVotes": 1,
            "points": 625
          },
          {
            "rank": 3,
            "school": "Jacksonville State",
            "conference": "OVC",
            "firstPlaceVotes": 0,
            "points": 585
          },
          {
            "rank": 4,
            "school": "South Dakota",
            "conference": "MVFC",
            "firstPlaceVotes": 0,
            "points": 561
          },
          {
            "rank": 5,
            "school": "Wofford",
            "conference": "Southern",
            "firstPlaceVotes": 0,
            "points": 548
          },
          {
            "rank": 6,
            "school": "Central Arkansas",
            "conference": "Southland",
            "firstPlaceVotes": 0,
            "points": 508
          },
          {
            "rank": 7,
            "school": "South Dakota State",
            "conference": "MVFC",
            "firstPlaceVotes": 0,
            "points": 463
          },
          {
            "rank": 8,
            "school": "Youngstown State",
            "conference": "MVFC",
            "firstPlaceVotes": 0,
            "points": 457
          },
          {
            "rank": 9,
            "school": "Sam Houston",
            "conference": "Southland",
            "firstPlaceVotes": 0,
            "points": 422
          },
          {
            "rank": 9,
            "school": "Eastern Washington",
            "conference": "Big Sky",
            "firstPlaceVotes": 0,
            "points": 422
          },
          {
            "rank": 11,
            "school": "North Carolina A&T",
            "conference": "MEAC",
            "firstPlaceVotes": 0,
            "points": 388
          },
          {
            "rank": 12,
            "school": "New Hampshire",
            "conference": "CAA",
            "firstPlaceVotes": 0,
            "points": 347
          },
          {
            "rank": 13,
            "school": "Richmond",
            "conference": "CAA",
            "firstPlaceVotes": 0,
            "points": 306
          },
          {
            "rank": 14,
            "school": "Villanova",
            "conference": "CAA",
            "firstPlaceVotes": 0,
            "points": 302
          },
          {
            "rank": 15,
            "school": "Illinois State",
            "conference": "MVFC",
            "firstPlaceVotes": 0,
            "points": 301
          },
          {
            "rank": 16,
            "school": "Weber State",
            "conference": "Big Sky",
            "firstPlaceVotes": 0,
            "points": 284
          },
          {
            "rank": 17,
            "school": "Western Illinois",
            "conference": "MVFC",
            "firstPlaceVotes": 0,
            "points": 256
          },
          {
            "rank": 18,
            "school": "Samford",
            "conference": "Southern",
            "firstPlaceVotes": 0,
            "points": 184
          },
          {
            "rank": 19,
            "school": "Grambling",
            "conference": "SWAC",
            "firstPlaceVotes": 0,
            "points": 167
          },
          {
            "rank": 20,
            "school": "Elon",
            "conference": "CAA",
            "firstPlaceVotes": 0,
            "points": 157
          },
          {
            "rank": 21,
            "school": "McNeese",
            "conference": "Southland",
            "firstPlaceVotes": 0,
            "points": 144
          },
          {
            "rank": 22,
            "school": "The Citadel",
            "conference": "Southern",
            "firstPlaceVotes": 0,
            "points": 88
          },
          {
            "rank": 23,
            "school": "Nicholls",
            "conference": "Southland",
            "firstPlaceVotes": 0,
            "points": 68
          },
          {
            "rank": 24,
            "school": "Northern Arizona",
            "conference": "Big Sky",
            "firstPlaceVotes": 0,
            "points": 40
          },
          {
            "rank": 25,
            "school": "Western Carolina",
            "conference": "Southern",
            "firstPlaceVotes": 0,
            "points": 36
          }
        ]
      },
      {
        "poll": "AFCA Division II Coaches Poll",
        "ranks": [
          {
            "rank": 1,
            "school": "Northwest Missouri St",
            "conference": "Mid America",
            "firstPlaceVotes": 34,
            "points": 850
          },
          {
            "rank": 2,
            "school": "Shepherd",
            "conference": "Mountain East",
            "firstPlaceVotes": 0,
            "points": 791
          },
          {
            "rank": 3,
            "school": "Indiana-Pennsylvania",
            "conference": "Pennsylvania State Athletic",
            "firstPlaceVotes": 0,
            "points": 782
          },
          {
            "rank": 4,
            "school": "Minnesota State Mankato",
            "conference": "Northern Sun",
            "firstPlaceVotes": 0,
            "points": 754
          },
          {
            "rank": 5,
            "school": "Midwestern State",
            "conference": "Lone Star",
            "firstPlaceVotes": 0,
            "points": 682
          },
          {
            "rank": 6,
            "school": "Indianapolis",
            "conference": "Great Lakes",
            "firstPlaceVotes": 0,
            "points": 678
          },
          {
            "rank": 7,
            "school": "Grand Valley State University",
            "conference": "GLIAC",
            "firstPlaceVotes": 0,
            "points": 635
          },
          {
            "rank": 8,
            "school": "Fort Hays State",
            "conference": "Mid America",
            "firstPlaceVotes": 0,
            "points": 616
          },
          {
            "rank": 9,
            "school": "Central Washington",
            "conference": "Great Northwest",
            "firstPlaceVotes": 0,
            "points": 572
          },
          {
            "rank": 10,
            "school": "East Texas A&M",
            "conference": "Lone Star",
            "firstPlaceVotes": 0,
            "points": 541
          },
          {
            "rank": 11,
            "school": "Winona State",
            "conference": "Northern Sun",
            "firstPlaceVotes": 0,
            "points": 494
          },
          {
            "rank": 12,
            "school": "Ferris State",
            "conference": "GLIAC",
            "firstPlaceVotes": 0,
            "points": 424
          },
          {
            "rank": 13,
            "school": "Ashland",
            "conference": "GLIAC",
            "firstPlaceVotes": 0,
            "points": 423
          },
          {
            "rank": 14,
            "school": "Assumption",
            "conference": "Northeast 10",
            "firstPlaceVotes": 0,
            "points": 406
          },
          {
            "rank": 15,
            "school": "Sioux Falls",
            "conference": "Northern Sun",
            "firstPlaceVotes": 0,
            "points": 352
          },
          {
            "rank": 16,
            "school": "Colorado Mesa",
            "conference": "Rocky Mountain",
            "firstPlaceVotes": 0,
            "points": 307
          },
          {
            "rank": 17,
            "school": "Slippery Rock",
            "conference": "Pennsylvania State Athletic",
            "firstPlaceVotes": 0,
            "points": 288
          },
          {
            "rank": 18,
            "school": "West Alabama",
            "conference": "Gulf South",
            "firstPlaceVotes": 0,
            "points": 271
          },
          {
            "rank": 19,
            "school": "Delta State",
            "conference": "Gulf South",
            "firstPlaceVotes": 0,
            "points": 263
          },
          {
            "rank": 20,
            "school": "Wingate",
            "conference": "South Atlantic",
            "firstPlaceVotes": 0,
            "points": 243
          },
          {
            "rank": 21,
            "school": "Virginia St",
            "conference": "CIAA",
            "firstPlaceVotes": 0,
            "points": 165
          },
          {
            "rank": 22,
            "school": "Humboldt State",
            "conference": "Great Northwest",
            "firstPlaceVotes": 0,
            "points": 154
          },
          {
            "rank": 23,
            "school": "Bowie State",
            "conference": "CIAA",
            "firstPlaceVotes": 0,
            "points": 95
          },
          {
            "rank": 24,
            "school": "Eastern New Mexico",
            "conference": "Lone Star",
            "firstPlaceVotes": 0,
            "points": 66
          },
          {
            "rank": 25,
            "school": "Southeastern Oklahoma State",
            "conference": "Great American",
            "firstPlaceVotes": 0,
            "points": 64
          }
        ]
      }
    ]
  }
]